collagraph_lsp/__init__.py
collagraph_lsp/completions.py
collagraph_lsp/server.py
collagraph_lsp-0.1.2.dist-info/METADATA
collagraph_lsp-0.1.2.dist-info/WHEEL
collagraph_lsp-0.1.2.dist-info/entry_points.txt
collagraph_lsp-0.1.2.dist-info/licenses/LICENSE
collagraph_lsp-0.1.2.dist-info/RECORD
