Metadata-Version: 2.4
Name: collagraph-lsp
Version: 0.1.2
Summary: LSP server for Collagraph (.cgx) files with ruff integration
Author-email: Berend Klein Haneveld <berendkleinhaneveld@gmail.com>
License-Expression: MIT
License-File: LICENSE
Requires-Python: >=3.10
Requires-Dist: collagraph>=0.8.0
Requires-Dist: jedi>=0.19.0
Requires-Dist: pygls>=2.0.0
Requires-Dist: ruff-cgx>=0.1.4
Requires-Dist: ruff>=0.14.0
